LICENSE
MANIFEST.in
README.rst
setup.py
ece/ECE.py
ece/Exposer.py
ece/__init__.py
ece.egg-info/PKG-INFO
ece.egg-info/SOURCES.txt
ece.egg-info/dependency_links.txt
ece.egg-info/top_level.txt