Metadata-Version: 1.0
Name: ece
Version: 0.6.4
Summary: Exposer Classifier Ensemble
Home-page: https://github.com/w4k2/ece
Author: Paweł Ksieniewicz
Author-email: pawel.ksieniewicz@pwr.edu.pl
License:                     GNU GENERAL PUBLIC LICENSE
